jigu/__init__.py
jigu/error.py
jigu/networks.py
jigu/terra.py
jigu/version.py
jigu/api/__init__.py
jigu/api/response.py
jigu/api/tendermint.py
jigu/api/tx.py
jigu/api/modules/__init__.py
jigu/api/modules/auth.py
jigu/api/modules/bank.py
jigu/api/modules/distribution.py
jigu/api/modules/gov.py
jigu/api/modules/market.py
jigu/api/modules/oracle.py
jigu/api/modules/slashing.py
jigu/api/modules/staking.py
jigu/api/modules/supply.py
jigu/api/modules/treasury.py
jigu/client/__init__.py
jigu/client/http.py
jigu/core/__init__.py
jigu/core/auth.py
jigu/core/block.py
jigu/core/denoms.py
jigu/core/gov.py
jigu/core/oracle.py
jigu/core/staking.py
jigu/core/transaction.py
jigu/core/treasury.py
jigu/core/msg/__init__.py
jigu/core/msg/bank.py
jigu/core/msg/distribution.py
jigu/core/msg/gov.py
jigu/core/msg/market.py
jigu/core/msg/oracle.py
jigu/core/msg/staking.py
jigu/core/sdk/__init__.py
jigu/core/sdk/coin.py
jigu/core/sdk/dec.py
jigu/core/sdk/timestamp.py
jigu/key/__init__.py
jigu/key/mnemonic.py
jigu/query/__init__.py
jigu/query/account.py
jigu/query/blocks.py
jigu/query/proposal.py
jigu/query/validator.py
jigu/query/wallet.py
jigu/util/__init__.py
jigu/util/validation.py
silt-0.0.12.dist-info/LICENSE
silt-0.0.12.dist-info/METADATA
silt-0.0.12.dist-info/WHEEL
silt-0.0.12.dist-info/top_level.txt
silt-0.0.12.dist-info/RECORD
