Metadata-Version: 2.1
Name: silt
Version: 0.0.12
Summary: Python SDK for Terra
Home-page: https://github.com/terra-project/jigu
Author: Terraform Labs, PTE
Author-email: william@terra.money, etienne@terra.money
License: MIT license
Keywords: terra,jigu,sdk,blockchain
Platform: UNKNOWN
Classifier: Development Status :: 2 - Pre-Alpha
Classifier: Intended Audience :: Developers
Classifier: License :: OSI Approved :: MIT License
Classifier: Natural Language :: English
Classifier: Programming Language :: Python :: 3
Classifier: Programming Language :: Python :: 3.6
Classifier: Programming Language :: Python :: 3.7
Classifier: Programming Language :: Python :: 3.8
Requires-Python: >=3.6
Requires-Dist: bip32utils (~=0.3.0)
Requires-Dist: mnemonic (~=0.18.0)
Requires-Dist: bech32 (~=1.1)
Requires-Dist: ecdsa (~=0.13.2)
Requires-Dist: requests (~=2.22)
Requires-Dist: wrapt (~=1.11.2)
Requires-Dist: python-dateutil (~=2.8.1)
Requires-Dist: pygments (~=2.5.2)
Requires-Dist: cached-property (~=1.5.1)
